pywup/__init__.py
pywup/configure.py
pywup/consts.py
pywup/wup.py
pywup/cmdtools/__init__.py
pywup/cmdtools/backup.py
pywup/cmdtools/bars.py
pywup/cmdtools/cluster.py
pywup/cmdtools/collect.py
pywup/cmdtools/conf.py
pywup/cmdtools/env.py
pywup/cmdtools/heatmap.py
pywup/cmdtools/menv.py
pywup/cmdtools/q.py
pywup/cmdtools/use.py
pywup/cmdtools/virtual.py
pywup/services/__init__.py
pywup/services/burn.py
pywup/services/cluster.py
pywup/services/cluster_burn.py
pywup/services/clusterfile.py
pywup/services/context.py
pywup/services/docker.py
pywup/services/env.py
pywup/services/envfile.py
pywup/services/io.py
pywup/services/menv.py
pywup/services/pbash.py
pywup/services/ssh.py
pywup/services/state_machine.py
pywup/services/system.py
pywup/services/virtual.py
pywup-0.0.38.dist-info/METADATA
pywup-0.0.38.dist-info/WHEEL
pywup-0.0.38.dist-info/entry_points.txt
pywup-0.0.38.dist-info/top_level.txt
pywup-0.0.38.dist-info/RECORD
