Metadata-Version: 2.1
Name: pywup
Version: 0.0.38
Summary: A small set of tools
Home-page: https://github.com/diegofps/pywup
Author: Diego Souza
Author-email: contact@wespa.com.br
License: UNKNOWN
Platform: UNKNOWN
Classifier: Programming Language :: Python :: 3
Classifier: License :: OSI Approved :: MIT License
Classifier: Operating System :: OS Independent
Requires-Dist: colorcet
Requires-Dist: tqdm
Requires-Dist: PyYAML
Provides-Extra: full
Requires-Dist: numpy ; extra == 'full'
Requires-Dist: matplotlib ; extra == 'full'
